ebook_crawler/__init__.py
ebook_crawler-2.1.8.dist-info/DESCRIPTION.rst
ebook_crawler-2.1.8.dist-info/METADATA
ebook_crawler-2.1.8.dist-info/RECORD
ebook_crawler-2.1.8.dist-info/WHEEL
ebook_crawler-2.1.8.dist-info/entry_points.txt
ebook_crawler-2.1.8.dist-info/metadata.json
ebook_crawler-2.1.8.dist-info/top_level.txt
